{
  "50": {
    "level": 50,
    "count": 5,
    "analysts": {
      "kaprik0rn3": 4,
      "barrysanders329": 1
    },
    "tickers": {
      "OKLO": 1,
      "TNX": 1,
      "SNDK": 1,
      "APLD": 1,
      "APP": 1
    },
    "biases": {
      "BULLISH": 1,
      "BEARISH": 0,
      "NEUTRAL": 4
    },
    "signal_types": {
      "LEVEL_WATCH": 3,
      "CHART_ANALYSIS": 2
    },
    "first_seen": "2026-02-14T02:39:27.022Z",
    "last_seen": "2026-04-10T13:52:55.978Z",
    "analyst_count": 2,
    "dominant_bias": "BULLISH",
    "confluence_bonus": 2
  },
  "60": {
    "level": 60,
    "count": 5,
    "analysts": {
      "kaprik0rn3": 3,
      "barrysanders329": 1,
      "general_dollars": 1
    },
    "tickers": {
      "QBTS": 1,
      "AAOI": 1,
      "INTC": 1,
      "LITE": 1,
      "SNDK": 1
    },
    "biases": {
      "BULLISH": 1,
      "BEARISH": 1,
      "NEUTRAL": 3
    },
    "signal_types": {
      "CHART_ANALYSIS": 1,
      "LEVEL_WATCH": 4
    },
    "first_seen": "2026-02-13T18:02:05.624Z",
    "last_seen": "2026-04-15T22:14:21.548Z",
    "analyst_count": 3,
    "dominant_bias": "NEUTRAL",
    "confluence_bonus": 2
  },
  "65": {
    "level": 65,
    "count": 1,
    "analysts": {
      "barrysanders329": 1
    },
    "tickers": {
      "PCALL": 1
    },
    "biases": {
      "BULLISH": 0,
      "BEARISH": 0,
      "NEUTRAL": 1
    },
    "signal_types": {
      "LEVEL_WATCH": 1
    },
    "first_seen": "2026-04-15T13:26:40.893Z",
    "last_seen": "2026-04-15T13:26:40.893Z",
    "analyst_count": 1,
    "dominant_bias": "NEUTRAL",
    "confluence_bonus": 0
  },
  "70": {
    "level": 70,
    "count": 2,
    "analysts": {
      "kaprik0rn3": 2
    },
    "tickers": {
      "LITE": 2
    },
    "biases": {
      "BULLISH": 0,
      "BEARISH": 0,
      "NEUTRAL": 2
    },
    "signal_types": {
      "LEVEL_WATCH": 2
    },
    "first_seen": "2026-03-24T15:49:22.375Z",
    "last_seen": "2026-04-02T14:16:20.578Z",
    "analyst_count": 1,
    "dominant_bias": "NEUTRAL",
    "confluence_bonus": 0
  },
  "75": {
    "level": 75,
    "count": 2,
    "analysts": {
      "kaprik0rn3": 2
    },
    "tickers": {
      "BTC": 1,
      "SNDK": 1
    },
    "biases": {
      "BULLISH": 0,
      "BEARISH": 0,
      "NEUTRAL": 2
    },
    "signal_types": {
      "CHART_ANALYSIS": 1,
      "LEVEL_WATCH": 1
    },
    "first_seen": "2026-04-01T17:37:04.442Z",
    "last_seen": "2026-04-17T13:21:07.815Z",
    "analyst_count": 1,
    "dominant_bias": "NEUTRAL",
    "confluence_bonus": 0
  },
  "80": {
    "level": 80,
    "count": 1,
    "analysts": {
      "barrysanders329": 1
    },
    "tickers": {
      "VIX": 1
    },
    "biases": {
      "BULLISH": 0,
      "BEARISH": 0,
      "NEUTRAL": 1
    },
    "signal_types": {
      "CHART_ANALYSIS": 1
    },
    "first_seen": "2026-04-02T12:51:05.173Z",
    "last_seen": "2026-04-02T12:51:05.173Z",
    "analyst_count": 1,
    "dominant_bias": "NEUTRAL",
    "confluence_bonus": 0
  },
  "85": {
    "level": 85,
    "count": 4,
    "analysts": {
      "kaprik0rn3": 1,
      "mathemeatloaf7": 2,
      "barrysanders329": 1
    },
    "tickers": {
      "SNDK": 1,
      "VIX": 2,
      "CVX": 1
    },
    "biases": {
      "BULLISH": 0,
      "BEARISH": 0,
      "NEUTRAL": 4
    },
    "signal_types": {
      "LEVEL_WATCH": 2,
      "CHART_ANALYSIS": 2
    },
    "first_seen": "2026-03-12T14:23:09.993Z",
    "last_seen": "2026-04-13T18:33:33.027Z",
    "analyst_count": 3,
    "dominant_bias": "NEUTRAL",
    "confluence_bonus": 2
  },
  "90": {
    "level": 90,
    "count": 2,
    "analysts": {
      "barrysanders329": 1,
      "kaprik0rn3": 1
    },
    "tickers": {
      "VIX": 1,
      "LMT": 1
    },
    "biases": {
      "BULLISH": 0,
      "BEARISH": 0,
      "NEUTRAL": 2
    },
    "signal_types": {
      "LEVEL_WATCH": 2
    },
    "first_seen": "2026-03-02T01:39:00.164Z",
    "last_seen": "2026-04-02T12:43:51.025Z",
    "analyst_count": 2,
    "dominant_bias": "NEUTRAL",
    "confluence_bonus": 1
  },
  "95": {
    "level": 95,
    "count": 1,
    "analysts": {
      "kaprik0rn3": 1
    },
    "tickers": {
      "LITE": 1
    },
    "biases": {
      "BULLISH": 0,
      "BEARISH": 0,
      "NEUTRAL": 1
    },
    "signal_types": {
      "LEVEL_WATCH": 1
    },
    "first_seen": "2026-03-20T14:15:07.012Z",
    "last_seen": "2026-03-20T14:15:07.012Z",
    "analyst_count": 1,
    "dominant_bias": "NEUTRAL",
    "confluence_bonus": 0
  },
  "100": {
    "level": 100,
    "count": 4,
    "analysts": {
      "kaprik0rn3": 3,
      "general_dollars": 1
    },
    "tickers": {
      "CAR": 1,
      "IBIT": 1,
      "CRCL": 1,
      "INTC": 1
    },
    "biases": {
      "BULLISH": 0,
      "BEARISH": 0,
      "NEUTRAL": 4
    },
    "signal_types": {
      "CHART_ANALYSIS": 1,
      "LEVEL_WATCH": 3
    },
    "first_seen": "2026-02-25T21:16:25.354Z",
    "last_seen": "2026-04-20T18:43:41.753Z",
    "analyst_count": 2,
    "dominant_bias": "NEUTRAL",
    "confluence_bonus": 2
  },
  "115": {
    "level": 115,
    "count": 2,
    "analysts": {
      "kaprik0rn3": 1,
      "barrysanders329": 1
    },
    "tickers": {
      "AAOI": 1,
      "ALAB": 1
    },
    "biases": {
      "BULLISH": 0,
      "BEARISH": 0,
      "NEUTRAL": 2
    },
    "signal_types": {
      "CHART_ANALYSIS": 1,
      "LEVEL_WATCH": 1
    },
    "first_seen": "2026-03-26T17:44:56.289Z",
    "last_seen": "2026-04-09T16:12:38.507Z",
    "analyst_count": 2,
    "dominant_bias": "NEUTRAL",
    "confluence_bonus": 1
  },
  "125": {
    "level": 125,
    "count": 1,
    "analysts": {
      "general_dollars": 1
    },
    "tickers": {
      "AMAT": 1
    },
    "biases": {
      "BULLISH": 0,
      "BEARISH": 0,
      "NEUTRAL": 1
    },
    "signal_types": {
      "LEVEL_WATCH": 1
    },
    "first_seen": "2026-02-14T02:28:05.757Z",
    "last_seen": "2026-02-14T02:28:05.757Z",
    "analyst_count": 1,
    "dominant_bias": "NEUTRAL",
    "confluence_bonus": 0
  },
  "130": {
    "level": 130,
    "count": 1,
    "analysts": {
      "kaprik0rn3": 1
    },
    "tickers": {
      "AAOI": 1
    },
    "biases": {
      "BULLISH": 1,
      "BEARISH": 0,
      "NEUTRAL": 0
    },
    "signal_types": {
      "LEVEL_WATCH": 1
    },
    "first_seen": "2026-04-08T16:26:17.955Z",
    "last_seen": "2026-04-08T16:26:17.955Z",
    "analyst_count": 1,
    "dominant_bias": "BULLISH",
    "confluence_bonus": 0
  },
  "135": {
    "level": 135,
    "count": 2,
    "analysts": {
      "kaprik0rn3": 2
    },
    "tickers": {
      "AAOI": 2
    },
    "biases": {
      "BULLISH": 1,
      "BEARISH": 0,
      "NEUTRAL": 1
    },
    "signal_types": {
      "LEVEL_WATCH": 1,
      "CHART_ANALYSIS": 1
    },
    "first_seen": "2026-03-24T18:08:41.697Z",
    "last_seen": "2026-04-08T16:48:27.018Z",
    "analyst_count": 1,
    "dominant_bias": "BULLISH",
    "confluence_bonus": 0
  },
  "140": {
    "level": 140,
    "count": 1,
    "analysts": {
      "barrysanders329": 1
    },
    "tickers": {
      "PLTR": 1
    },
    "biases": {
      "BULLISH": 0,
      "BEARISH": 0,
      "NEUTRAL": 1
    },
    "signal_types": {
      "LEVEL_WATCH": 1
    },
    "first_seen": "2026-04-13T18:11:43.538Z",
    "last_seen": "2026-04-13T18:11:43.538Z",
    "analyst_count": 1,
    "dominant_bias": "NEUTRAL",
    "confluence_bonus": 0
  },
  "155": {
    "level": 155,
    "count": 3,
    "analysts": {
      "kaprik0rn3": 1,
      "barrysanders329": 2
    },
    "tickers": {
      "AAOI": 1,
      "BE": 2
    },
    "biases": {
      "BULLISH": 0,
      "BEARISH": 0,
      "NEUTRAL": 3
    },
    "signal_types": {
      "CHART_ANALYSIS": 2,
      "LEVEL_WATCH": 1
    },
    "first_seen": "2026-02-10T18:33:32.671Z",
    "last_seen": "2026-04-09T16:12:38.507Z",
    "analyst_count": 2,
    "dominant_bias": "NEUTRAL",
    "confluence_bonus": 2
  },
  "160": {
    "level": 160,
    "count": 2,
    "analysts": {
      "kaprik0rn3": 2
    },
    "tickers": {
      "ARM": 2
    },
    "biases": {
      "BULLISH": 0,
      "BEARISH": 1,
      "NEUTRAL": 1
    },
    "signal_types": {
      "LEVEL_WATCH": 2
    },
    "first_seen": "2026-03-25T14:04:35.299Z",
    "last_seen": "2026-03-25T15:16:52.270Z",
    "analyst_count": 1,
    "dominant_bias": "BEARISH",
    "confluence_bonus": 0
  },
  "170": {
    "level": 170,
    "count": 1,
    "analysts": {
      "barrysanders329": 1
    },
    "tickers": {
      "AMD": 1
    },
    "biases": {
      "BULLISH": 0,
      "BEARISH": 0,
      "NEUTRAL": 1
    },
    "signal_types": {
      "CHART_ANALYSIS": 1
    },
    "first_seen": "2026-02-23T14:34:02.938Z",
    "last_seen": "2026-02-23T14:34:02.938Z",
    "analyst_count": 1,
    "dominant_bias": "NEUTRAL",
    "confluence_bonus": 0
  },
  "175": {
    "level": 175,
    "count": 1,
    "analysts": {
      "kaprik0rn3": 1
    },
    "tickers": {
      "COIN": 1
    },
    "biases": {
      "BULLISH": 0,
      "BEARISH": 0,
      "NEUTRAL": 1
    },
    "signal_types": {
      "LEVEL_WATCH": 1
    },
    "first_seen": "2026-02-25T15:43:36.198Z",
    "last_seen": "2026-02-25T15:43:36.198Z",
    "analyst_count": 1,
    "dominant_bias": "NEUTRAL",
    "confluence_bonus": 0
  },
  "180": {
    "level": 180,
    "count": 2,
    "analysts": {
      "kaprik0rn3": 2
    },
    "tickers": {
      "LMAO": 1,
      "COIN": 1
    },
    "biases": {
      "BULLISH": 0,
      "BEARISH": 0,
      "NEUTRAL": 2
    },
    "signal_types": {
      "LEVEL_WATCH": 2
    },
    "first_seen": "2026-02-25T16:29:23.569Z",
    "last_seen": "2026-04-15T13:10:50.473Z",
    "analyst_count": 1,
    "dominant_bias": "NEUTRAL",
    "confluence_bonus": 0
  },
  "185": {
    "level": 185,
    "count": 4,
    "analysts": {
      "kaprik0rn3": 4
    },
    "tickers": {
      "NVDA": 2,
      "ARM": 1,
      "COIN": 1
    },
    "biases": {
      "BULLISH": 0,
      "BEARISH": 1,
      "NEUTRAL": 3
    },
    "signal_types": {
      "LEVEL_WATCH": 4
    },
    "first_seen": "2026-02-25T17:40:58.181Z",
    "last_seen": "2026-04-10T13:47:59.344Z",
    "analyst_count": 1,
    "dominant_bias": "BEARISH",
    "confluence_bonus": 1
  },
  "190": {
    "level": 190,
    "count": 2,
    "analysts": {
      "kaprik0rn3": 1,
      "barrysanders329": 1
    },
    "tickers": {
      "COIN": 1,
      "AMD": 1
    },
    "biases": {
      "BULLISH": 0,
      "BEARISH": 0,
      "NEUTRAL": 2
    },
    "signal_types": {
      "LEVEL_WATCH": 1,
      "CHART_ANALYSIS": 1
    },
    "first_seen": "2026-02-23T14:34:02.938Z",
    "last_seen": "2026-03-06T15:54:16.253Z",
    "analyst_count": 2,
    "dominant_bias": "NEUTRAL",
    "confluence_bonus": 1
  },
  "195": {
    "level": 195,
    "count": 1,
    "analysts": {
      "kaprik0rn3": 1
    },
    "tickers": {
      "NVDA": 1
    },
    "biases": {
      "BULLISH": 0,
      "BEARISH": 0,
      "NEUTRAL": 1
    },
    "signal_types": {
      "CHART_ANALYSIS": 1
    },
    "first_seen": "2026-02-24T22:28:45.671Z",
    "last_seen": "2026-02-24T22:28:45.671Z",
    "analyst_count": 1,
    "dominant_bias": "NEUTRAL",
    "confluence_bonus": 0
  },
  "200": {
    "level": 200,
    "count": 2,
    "analysts": {
      "barrysanders329": 2
    },
    "tickers": {
      "MAGS": 1,
      "BE": 1
    },
    "biases": {
      "BULLISH": 1,
      "BEARISH": 0,
      "NEUTRAL": 1
    },
    "signal_types": {
      "CHART_ANALYSIS": 2
    },
    "first_seen": "2026-02-09T17:16:19.699Z",
    "last_seen": "2026-03-12T13:48:30.729Z",
    "analyst_count": 1,
    "dominant_bias": "BULLISH",
    "confluence_bonus": 0
  },
  "215": {
    "level": 215,
    "count": 4,
    "analysts": {
      "kaprik0rn3": 3,
      "barrysanders329": 1
    },
    "tickers": {
      "COIN": 3,
      "NVDA": 1
    },
    "biases": {
      "BULLISH": 0,
      "BEARISH": 1,
      "NEUTRAL": 3
    },
    "signal_types": {
      "LEVEL_WATCH": 4
    },
    "first_seen": "2026-02-25T20:23:05.174Z",
    "last_seen": "2026-04-17T13:01:37.727Z",
    "analyst_count": 2,
    "dominant_bias": "BEARISH",
    "confluence_bonus": 2
  },
  "225": {
    "level": 225,
    "count": 1,
    "analysts": {
      "kaprik0rn3": 1
    },
    "tickers": {
      "COIN": 1
    },
    "biases": {
      "BULLISH": 0,
      "BEARISH": 0,
      "NEUTRAL": 1
    },
    "signal_types": {
      "LEVEL_WATCH": 1
    },
    "first_seen": "2026-03-04T17:04:51.596Z",
    "last_seen": "2026-03-04T17:04:51.596Z",
    "analyst_count": 1,
    "dominant_bias": "NEUTRAL",
    "confluence_bonus": 0
  },
  "230": {
    "level": 230,
    "count": 2,
    "analysts": {
      "mathemeatloaf7": 2
    },
    "tickers": {
      "IWM": 2
    },
    "biases": {
      "BULLISH": 0,
      "BEARISH": 0,
      "NEUTRAL": 2
    },
    "signal_types": {
      "LEVEL_WATCH": 2
    },
    "first_seen": "2026-03-30T20:34:10.647Z",
    "last_seen": "2026-03-30T20:34:10.647Z",
    "analyst_count": 1,
    "dominant_bias": "NEUTRAL",
    "confluence_bonus": 0
  },
  "250": {
    "level": 250,
    "count": 1,
    "analysts": {
      "kaprik0rn3": 1
    },
    "tickers": {
      "TSLA": 1
    },
    "biases": {
      "BULLISH": 0,
      "BEARISH": 1,
      "NEUTRAL": 0
    },
    "signal_types": {
      "CHART_ANALYSIS": 1
    },
    "first_seen": "2026-03-20T00:38:04.366Z",
    "last_seen": "2026-03-20T00:38:04.366Z",
    "analyst_count": 1,
    "dominant_bias": "BEARISH",
    "confluence_bonus": 0
  },
  "255": {
    "level": 255,
    "count": 1,
    "analysts": {
      "mathemeatloaf7": 1
    },
    "tickers": {
      "IWM": 1
    },
    "biases": {
      "BULLISH": 0,
      "BEARISH": 0,
      "NEUTRAL": 1
    },
    "signal_types": {
      "LEVEL_WATCH": 1
    },
    "first_seen": "2026-04-21T17:13:24.976Z",
    "last_seen": "2026-04-21T17:13:24.976Z",
    "analyst_count": 1,
    "dominant_bias": "NEUTRAL",
    "confluence_bonus": 0
  },
  "260": {
    "level": 260,
    "count": 2,
    "analysts": {
      "mathemeatloaf7": 1,
      "kaprik0rn3": 1
    },
    "tickers": {
      "IWM": 1,
      "DUOL": 1
    },
    "biases": {
      "BULLISH": 1,
      "BEARISH": 0,
      "NEUTRAL": 1
    },
    "signal_types": {
      "LEVEL_WATCH": 1,
      "CHART_ANALYSIS": 1
    },
    "first_seen": "2026-02-11T17:57:18.181Z",
    "last_seen": "2026-04-21T17:13:24.976Z",
    "analyst_count": 2,
    "dominant_bias": "BULLISH",
    "confluence_bonus": 1
  },
  "265": {
    "level": 265,
    "count": 1,
    "analysts": {
      "kaprik0rn3": 1
    },
    "tickers": {
      "TSLA": 1
    },
    "biases": {
      "BULLISH": 0,
      "BEARISH": 1,
      "NEUTRAL": 0
    },
    "signal_types": {
      "CHART_ANALYSIS": 1
    },
    "first_seen": "2026-03-20T00:38:04.366Z",
    "last_seen": "2026-03-20T00:38:04.366Z",
    "analyst_count": 1,
    "dominant_bias": "BEARISH",
    "confluence_bonus": 0
  },
  "270": {
    "level": 270,
    "count": 2,
    "analysts": {
      "mathemeatloaf7": 1,
      "barrysanders329": 1
    },
    "tickers": {
      "IWM": 1,
      "QQQ": 1
    },
    "biases": {
      "BULLISH": 0,
      "BEARISH": 0,
      "NEUTRAL": 2
    },
    "signal_types": {
      "LEVEL_WATCH": 1,
      "CHART_ANALYSIS": 1
    },
    "first_seen": "2026-02-14T04:48:19.516Z",
    "last_seen": "2026-04-21T17:13:24.976Z",
    "analyst_count": 2,
    "dominant_bias": "NEUTRAL",
    "confluence_bonus": 1
  },
  "285": {
    "level": 285,
    "count": 1,
    "analysts": {
      "barrysanders329": 1
    },
    "tickers": {
      "FTAI": 1
    },
    "biases": {
      "BULLISH": 0,
      "BEARISH": 0,
      "NEUTRAL": 1
    },
    "signal_types": {
      "CHART_ANALYSIS": 1
    },
    "first_seen": "2026-02-17T03:14:52.970Z",
    "last_seen": "2026-02-17T03:14:52.970Z",
    "analyst_count": 1,
    "dominant_bias": "NEUTRAL",
    "confluence_bonus": 0
  },
  "300": {
    "level": 300,
    "count": 1,
    "analysts": {
      "barrysanders329": 1
    },
    "tickers": {
      "FTAI": 1
    },
    "biases": {
      "BULLISH": 0,
      "BEARISH": 0,
      "NEUTRAL": 1
    },
    "signal_types": {
      "LEVEL_WATCH": 1
    },
    "first_seen": "2026-02-17T16:24:57.484Z",
    "last_seen": "2026-02-17T16:24:57.484Z",
    "analyst_count": 1,
    "dominant_bias": "NEUTRAL",
    "confluence_bonus": 0
  },
  "320": {
    "level": 320,
    "count": 1,
    "analysts": {
      "barrysanders329": 1
    },
    "tickers": {
      "QQQ": 1
    },
    "biases": {
      "BULLISH": 0,
      "BEARISH": 0,
      "NEUTRAL": 1
    },
    "signal_types": {
      "CHART_ANALYSIS": 1
    },
    "first_seen": "2026-02-14T04:48:19.516Z",
    "last_seen": "2026-02-14T04:48:19.516Z",
    "analyst_count": 1,
    "dominant_bias": "NEUTRAL",
    "confluence_bonus": 0
  },
  "340": {
    "level": 340,
    "count": 3,
    "analysts": {
      "barrysanders329": 3
    },
    "tickers": {
      "TSLA": 3
    },
    "biases": {
      "BULLISH": 0,
      "BEARISH": 0,
      "NEUTRAL": 3
    },
    "signal_types": {
      "LEVEL_WATCH": 3
    },
    "first_seen": "2026-03-26T19:21:08.690Z",
    "last_seen": "2026-03-30T14:41:22.996Z",
    "analyst_count": 1,
    "dominant_bias": "NEUTRAL",
    "confluence_bonus": 1
  },
  "350": {
    "level": 350,
    "count": 2,
    "analysts": {
      "barrysanders329": 2
    },
    "tickers": {
      "TSLA": 1,
      "QQQ": 1
    },
    "biases": {
      "BULLISH": 0,
      "BEARISH": 0,
      "NEUTRAL": 2
    },
    "signal_types": {
      "CHART_ANALYSIS": 2
    },
    "first_seen": "2026-02-14T04:48:19.516Z",
    "last_seen": "2026-03-27T13:34:55.165Z",
    "analyst_count": 1,
    "dominant_bias": "NEUTRAL",
    "confluence_bonus": 0
  },
  "355": {
    "level": 355,
    "count": 1,
    "analysts": {
      "barrysanders329": 1
    },
    "tickers": {
      "TSLA": 1
    },
    "biases": {
      "BULLISH": 0,
      "BEARISH": 0,
      "NEUTRAL": 1
    },
    "signal_types": {
      "CHART_ANALYSIS": 1
    },
    "first_seen": "2026-03-26T14:43:08.678Z",
    "last_seen": "2026-03-26T14:43:08.678Z",
    "analyst_count": 1,
    "dominant_bias": "NEUTRAL",
    "confluence_bonus": 0
  },
  "360": {
    "level": 360,
    "count": 3,
    "analysts": {
      "barrysanders329": 3
    },
    "tickers": {
      "TSLA": 2,
      "QQQ": 1
    },
    "biases": {
      "BULLISH": 0,
      "BEARISH": 0,
      "NEUTRAL": 3
    },
    "signal_types": {
      "LEVEL_WATCH": 2,
      "CHART_ANALYSIS": 1
    },
    "first_seen": "2026-02-14T04:48:19.516Z",
    "last_seen": "2026-03-30T16:58:13.323Z",
    "analyst_count": 1,
    "dominant_bias": "NEUTRAL",
    "confluence_bonus": 1
  },
  "365": {
    "level": 365,
    "count": 2,
    "analysts": {
      "barrysanders329": 1,
      "kaprik0rn3": 1
    },
    "tickers": {
      "TSLA": 2
    },
    "biases": {
      "BULLISH": 0,
      "BEARISH": 1,
      "NEUTRAL": 1
    },
    "signal_types": {
      "CHART_ANALYSIS": 2
    },
    "first_seen": "2026-03-20T00:38:04.366Z",
    "last_seen": "2026-03-26T14:43:08.678Z",
    "analyst_count": 2,
    "dominant_bias": "BEARISH",
    "confluence_bonus": 1
  },
  "370": {
    "level": 370,
    "count": 1,
    "analysts": {
      "barrysanders329": 1
    },
    "tickers": {
      "MSFT": 1
    },
    "biases": {
      "BULLISH": 0,
      "BEARISH": 0,
      "NEUTRAL": 1
    },
    "signal_types": {
      "LEVEL_WATCH": 1
    },
    "first_seen": "2026-02-11T15:15:53.823Z",
    "last_seen": "2026-02-11T15:15:53.823Z",
    "analyst_count": 1,
    "dominant_bias": "NEUTRAL",
    "confluence_bonus": 0
  },
  "380": {
    "level": 380,
    "count": 1,
    "analysts": {
      "mathemeatloaf7": 1
    },
    "tickers": {
      "SPY": 1
    },
    "biases": {
      "BULLISH": 0,
      "BEARISH": 0,
      "NEUTRAL": 1
    },
    "signal_types": {
      "CHART_ANALYSIS": 1
    },
    "first_seen": "2026-02-17T17:24:49.605Z",
    "last_seen": "2026-02-17T17:24:49.605Z",
    "analyst_count": 1,
    "dominant_bias": "NEUTRAL",
    "confluence_bonus": 0
  },
  "390": {
    "level": 390,
    "count": 1,
    "analysts": {
      "kaprik0rn3": 1
    },
    "tickers": {
      "APP": 1
    },
    "biases": {
      "BULLISH": 0,
      "BEARISH": 0,
      "NEUTRAL": 1
    },
    "signal_types": {
      "CHART_ANALYSIS": 1
    },
    "first_seen": "2026-02-14T02:39:27.022Z",
    "last_seen": "2026-02-14T02:39:27.022Z",
    "analyst_count": 1,
    "dominant_bias": "NEUTRAL",
    "confluence_bonus": 0
  },
  "395": {
    "level": 395,
    "count": 3,
    "analysts": {
      "kaprik0rn3": 1,
      "mathemeatloaf7": 1,
      "barrysanders329": 1
    },
    "tickers": {
      "GLD": 1,
      "DIA": 1,
      "MSFT": 1
    },
    "biases": {
      "BULLISH": 1,
      "BEARISH": 1,
      "NEUTRAL": 1
    },
    "signal_types": {
      "LEVEL_WATCH": 2,
      "CHART_ANALYSIS": 1
    },
    "first_seen": "2026-03-13T19:43:02.037Z",
    "last_seen": "2026-03-20T20:42:58.761Z",
    "analyst_count": 3,
    "dominant_bias": "NEUTRAL",
    "confluence_bonus": 2
  },
  "400": {
    "level": 400,
    "count": 4,
    "analysts": {
      "kaprik0rn3": 2,
      "barrysanders329": 2
    },
    "tickers": {
      "GLD": 1,
      "MSFT": 1,
      "TSLA": 1,
      "QQQ": 1
    },
    "biases": {
      "BULLISH": 0,
      "BEARISH": 1,
      "NEUTRAL": 3
    },
    "signal_types": {
      "LEVEL_WATCH": 3,
      "CHART_ANALYSIS": 1
    },
    "first_seen": "2026-02-14T04:48:19.516Z",
    "last_seen": "2026-03-20T20:42:58.761Z",
    "analyst_count": 2,
    "dominant_bias": "BEARISH",
    "confluence_bonus": 2
  },
  "410": {
    "level": 410,
    "count": 1,
    "analysts": {
      "kaprik0rn3": 1
    },
    "tickers": {
      "CVNA": 1
    },
    "biases": {
      "BULLISH": 1,
      "BEARISH": 0,
      "NEUTRAL": 0
    },
    "signal_types": {
      "LEVEL_WATCH": 1
    },
    "first_seen": "2026-04-20T19:55:31.993Z",
    "last_seen": "2026-04-20T19:55:31.993Z",
    "analyst_count": 1,
    "dominant_bias": "BULLISH",
    "confluence_bonus": 0
  },
  "435": {
    "level": 435,
    "count": 1,
    "analysts": {
      "mathemeatloaf7": 1
    },
    "tickers": {
      "DIA": 1
    },
    "biases": {
      "BULLISH": 1,
      "BEARISH": 0,
      "NEUTRAL": 0
    },
    "signal_types": {
      "CHART_ANALYSIS": 1
    },
    "first_seen": "2026-03-19T18:53:03.660Z",
    "last_seen": "2026-03-19T18:53:03.660Z",
    "analyst_count": 1,
    "dominant_bias": "BULLISH",
    "confluence_bonus": 0
  },
  "450": {
    "level": 450,
    "count": 2,
    "analysts": {
      "mathemeatloaf7": 1,
      "barrysanders329": 1
    },
    "tickers": {
      "DIA": 1,
      "MSFT": 1
    },
    "biases": {
      "BULLISH": 2,
      "BEARISH": 0,
      "NEUTRAL": 0
    },
    "signal_types": {
      "CHART_ANALYSIS": 2
    },
    "first_seen": "2026-02-26T14:26:58.523Z",
    "last_seen": "2026-03-19T18:53:03.660Z",
    "analyst_count": 2,
    "dominant_bias": "BULLISH",
    "confluence_bonus": 1
  },
  "455": {
    "level": 455,
    "count": 1,
    "analysts": {
      "kaprik0rn3": 1
    },
    "tickers": {
      "GLD": 1
    },
    "biases": {
      "BULLISH": 0,
      "BEARISH": 0,
      "NEUTRAL": 1
    },
    "signal_types": {
      "LEVEL_WATCH": 1
    },
    "first_seen": "2026-03-16T16:28:13.577Z",
    "last_seen": "2026-03-16T16:28:13.577Z",
    "analyst_count": 1,
    "dominant_bias": "NEUTRAL",
    "confluence_bonus": 0
  },
  "460": {
    "level": 460,
    "count": 1,
    "analysts": {
      "kaprik0rn3": 1
    },
    "tickers": {
      "APP": 1
    },
    "biases": {
      "BULLISH": 1,
      "BEARISH": 0,
      "NEUTRAL": 0
    },
    "signal_types": {
      "CHART_ANALYSIS": 1
    },
    "first_seen": "2026-02-14T02:43:31.134Z",
    "last_seen": "2026-02-14T02:43:31.134Z",
    "analyst_count": 1,
    "dominant_bias": "BULLISH",
    "confluence_bonus": 0
  },
  "465": {
    "level": 465,
    "count": 3,
    "analysts": {
      "mathemeatloaf7": 3
    },
    "tickers": {
      "DIA": 3
    },
    "biases": {
      "BULLISH": 0,
      "BEARISH": 0,
      "NEUTRAL": 3
    },
    "signal_types": {
      "CHART_ANALYSIS": 3
    },
    "first_seen": "2026-03-17T23:59:01.234Z",
    "last_seen": "2026-03-18T14:51:09.016Z",
    "analyst_count": 1,
    "dominant_bias": "NEUTRAL",
    "confluence_bonus": 1
  },
  "480": {
    "level": 480,
    "count": 1,
    "analysts": {
      "barrysanders329": 1
    },
    "tickers": {
      "QQQ": 1
    },
    "biases": {
      "BULLISH": 0,
      "BEARISH": 0,
      "NEUTRAL": 1
    },
    "signal_types": {
      "CHART_ANALYSIS": 1
    },
    "first_seen": "2026-02-14T04:48:19.516Z",
    "last_seen": "2026-02-14T04:48:19.516Z",
    "analyst_count": 1,
    "dominant_bias": "NEUTRAL",
    "confluence_bonus": 0
  },
  "500": {
    "level": 500,
    "count": 2,
    "analysts": {
      "kaprik0rn3": 2
    },
    "tickers": {
      "META": 1,
      "DUOL": 1
    },
    "biases": {
      "BULLISH": 1,
      "BEARISH": 0,
      "NEUTRAL": 1
    },
    "signal_types": {
      "CHART_ANALYSIS": 2
    },
    "first_seen": "2026-02-11T17:57:18.181Z",
    "last_seen": "2026-03-26T18:24:28.401Z",
    "analyst_count": 1,
    "dominant_bias": "BULLISH",
    "confluence_bonus": 0
  },
  "530": {
    "level": 530,
    "count": 1,
    "analysts": {
      "mathemeatloaf7": 1
    },
    "tickers": {
      "SPY": 1
    },
    "biases": {
      "BULLISH": 0,
      "BEARISH": 0,
      "NEUTRAL": 1
    },
    "signal_types": {
      "LEVEL_WATCH": 1
    },
    "first_seen": "2026-03-12T20:17:35.679Z",
    "last_seen": "2026-03-12T20:17:35.679Z",
    "analyst_count": 1,
    "dominant_bias": "NEUTRAL",
    "confluence_bonus": 0
  },
  "540": {
    "level": 540,
    "count": 2,
    "analysts": {
      "kaprik0rn3": 1,
      "mathemeatloaf7": 1
    },
    "tickers": {
      "META": 1,
      "DIA": 1
    },
    "biases": {
      "BULLISH": 1,
      "BEARISH": 0,
      "NEUTRAL": 1
    },
    "signal_types": {
      "LEVEL_WATCH": 1,
      "CHART_ANALYSIS": 1
    },
    "first_seen": "2026-03-19T18:53:03.660Z",
    "last_seen": "2026-03-26T18:20:04.479Z",
    "analyst_count": 2,
    "dominant_bias": "BULLISH",
    "confluence_bonus": 1
  },
  "545": {
    "level": 545,
    "count": 1,
    "analysts": {
      "kaprik0rn3": 1
    },
    "tickers": {
      "APP": 1
    },
    "biases": {
      "BULLISH": 0,
      "BEARISH": 0,
      "NEUTRAL": 1
    },
    "signal_types": {
      "CHART_ANALYSIS": 1
    },
    "first_seen": "2026-02-14T02:39:27.022Z",
    "last_seen": "2026-02-14T02:39:27.022Z",
    "analyst_count": 1,
    "dominant_bias": "NEUTRAL",
    "confluence_bonus": 0
  },
  "560": {
    "level": 560,
    "count": 1,
    "analysts": {
      "mathemeatloaf7": 1
    },
    "tickers": {
      "QQQ": 1
    },
    "biases": {
      "BULLISH": 0,
      "BEARISH": 0,
      "NEUTRAL": 1
    },
    "signal_types": {
      "LEVEL_WATCH": 1
    },
    "first_seen": "2026-03-27T14:38:16.358Z",
    "last_seen": "2026-03-27T14:38:16.358Z",
    "analyst_count": 1,
    "dominant_bias": "NEUTRAL",
    "confluence_bonus": 0
  },
  "565": {
    "level": 565,
    "count": 3,
    "analysts": {
      "mathemeatloaf7": 3
    },
    "tickers": {
      "QQQ": 2,
      "SPY": 1
    },
    "biases": {
      "BULLISH": 0,
      "BEARISH": 0,
      "NEUTRAL": 3
    },
    "signal_types": {
      "LEVEL_WATCH": 3
    },
    "first_seen": "2026-03-12T20:17:35.679Z",
    "last_seen": "2026-03-31T16:01:31.800Z",
    "analyst_count": 1,
    "dominant_bias": "NEUTRAL",
    "confluence_bonus": 1
  },
  "575": {
    "level": 575,
    "count": 2,
    "analysts": {
      "mathemeatloaf7": 2
    },
    "tickers": {
      "QQQ": 2
    },
    "biases": {
      "BULLISH": 0,
      "BEARISH": 0,
      "NEUTRAL": 2
    },
    "signal_types": {
      "LEVEL_WATCH": 1,
      "CHART_ANALYSIS": 1
    },
    "first_seen": "2026-03-26T16:19:21.855Z",
    "last_seen": "2026-03-26T18:08:37.585Z",
    "analyst_count": 1,
    "dominant_bias": "NEUTRAL",
    "confluence_bonus": 0
  },
  "580": {
    "level": 580,
    "count": 6,
    "analysts": {
      "kaprik0rn3": 2,
      "mathemeatloaf7": 2,
      "barrysanders329": 2
    },
    "tickers": {
      "CAR": 1,
      "QQQ": 3,
      "SPY": 1,
      "META": 1
    },
    "biases": {
      "BULLISH": 0,
      "BEARISH": 1,
      "NEUTRAL": 5
    },
    "signal_types": {
      "CHART_ANALYSIS": 2,
      "LEVEL_WATCH": 4
    },
    "first_seen": "2026-02-13T12:37:56.469Z",
    "last_seen": "2026-04-20T18:43:41.753Z",
    "analyst_count": 3,
    "dominant_bias": "BEARISH",
    "confluence_bonus": 2
  },
  "585": {
    "level": 585,
    "count": 1,
    "analysts": {
      "mathemeatloaf7": 1
    },
    "tickers": {
      "QQQ": 1
    },
    "biases": {
      "BULLISH": 0,
      "BEARISH": 0,
      "NEUTRAL": 1
    },
    "signal_types": {
      "CHART_ANALYSIS": 1
    },
    "first_seen": "2026-03-26T16:19:21.855Z",
    "last_seen": "2026-03-26T16:19:21.855Z",
    "analyst_count": 1,
    "dominant_bias": "NEUTRAL",
    "confluence_bonus": 0
  },
  "590": {
    "level": 590,
    "count": 6,
    "analysts": {
      "mathemeatloaf7": 6
    },
    "tickers": {
      "DIA": 1,
      "SPY": 3,
      "QQQ": 2
    },
    "biases": {
      "BULLISH": 0,
      "BEARISH": 1,
      "NEUTRAL": 5
    },
    "signal_types": {
      "CHART_ANALYSIS": 1,
      "LEVEL_WATCH": 5
    },
    "first_seen": "2026-02-12T21:02:45.219Z",
    "last_seen": "2026-03-18T19:24:34.209Z",
    "analyst_count": 1,
    "dominant_bias": "BEARISH",
    "confluence_bonus": 1
  },
  "595": {
    "level": 595,
    "count": 2,
    "analysts": {
      "mathemeatloaf7": 2
    },
    "tickers": {
      "SPY": 1,
      "QQQ": 1
    },
    "biases": {
      "BULLISH": 0,
      "BEARISH": 2,
      "NEUTRAL": 0
    },
    "signal_types": {
      "CHART_ANALYSIS": 2
    },
    "first_seen": "2026-03-18T18:54:50.572Z",
    "last_seen": "2026-04-02T14:07:18.935Z",
    "analyst_count": 1,
    "dominant_bias": "BEARISH",
    "confluence_bonus": 0
  },
  "600": {
    "level": 600,
    "count": 2,
    "analysts": {
      "barrysanders329": 1,
      "mathemeatloaf7": 1
    },
    "tickers": {
      "QQQ": 1,
      "SPY": 1
    },
    "biases": {
      "BULLISH": 1,
      "BEARISH": 0,
      "NEUTRAL": 1
    },
    "signal_types": {
      "LEVEL_WATCH": 1,
      "CHART_ANALYSIS": 1
    },
    "first_seen": "2026-02-23T17:42:36.972Z",
    "last_seen": "2026-03-06T18:05:44.815Z",
    "analyst_count": 2,
    "dominant_bias": "BULLISH",
    "confluence_bonus": 1
  },
  "605": {
    "level": 605,
    "count": 8,
    "analysts": {
      "mathemeatloaf7": 8
    },
    "tickers": {
      "SPY": 3,
      "QQQ": 5
    },
    "biases": {
      "BULLISH": 0,
      "BEARISH": 6,
      "NEUTRAL": 2
    },
    "signal_types": {
      "LEVEL_WATCH": 5,
      "CHART_ANALYSIS": 3
    },
    "first_seen": "2026-02-13T17:05:17.683Z",
    "last_seen": "2026-03-17T17:12:02.537Z",
    "analyst_count": 1,
    "dominant_bias": "BEARISH",
    "confluence_bonus": 2
  },
  "610": {
    "level": 610,
    "count": 18,
    "analysts": {
      "mathemeatloaf7": 14,
      "kaprik0rn3": 3,
      "barrysanders329": 1
    },
    "tickers": {
      "SPY": 3,
      "QQQ": 15
    },
    "biases": {
      "BULLISH": 0,
      "BEARISH": 7,
      "NEUTRAL": 11
    },
    "signal_types": {
      "LEVEL_WATCH": 11,
      "CHART_ANALYSIS": 7
    },
    "first_seen": "2026-02-11T15:15:43.707Z",
    "last_seen": "2026-03-19T18:42:26.766Z",
    "analyst_count": 3,
    "dominant_bias": "BEARISH",
    "confluence_bonus": 3
  },
  "615": {
    "level": 615,
    "count": 12,
    "analysts": {
      "mathemeatloaf7": 12
    },
    "tickers": {
      "SPY": 5,
      "DIA": 1,
      "QQQ": 5,
      "VIX": 1
    },
    "biases": {
      "BULLISH": 1,
      "BEARISH": 2,
      "NEUTRAL": 9
    },
    "signal_types": {
      "LEVEL_WATCH": 7,
      "CHART_ANALYSIS": 5
    },
    "first_seen": "2026-01-29T14:55:11.446Z",
    "last_seen": "2026-03-19T18:53:03.660Z",
    "analyst_count": 1,
    "dominant_bias": "BEARISH",
    "confluence_bonus": 2
  },
  "620": {
    "level": 620,
    "count": 2,
    "analysts": {
      "mathemeatloaf7": 2
    },
    "tickers": {
      "VIX": 1,
      "QQQ": 1
    },
    "biases": {
      "BULLISH": 0,
      "BEARISH": 1,
      "NEUTRAL": 1
    },
    "signal_types": {
      "CHART_ANALYSIS": 2
    },
    "first_seen": "2026-01-29T14:55:11.446Z",
    "last_seen": "2026-02-09T15:19:53.688Z",
    "analyst_count": 1,
    "dominant_bias": "BEARISH",
    "confluence_bonus": 0
  },
  "625": {
    "level": 625,
    "count": 3,
    "analysts": {
      "mathemeatloaf7": 3
    },
    "tickers": {
      "QQQ": 3
    },
    "biases": {
      "BULLISH": 0,
      "BEARISH": 2,
      "NEUTRAL": 1
    },
    "signal_types": {
      "CHART_ANALYSIS": 3
    },
    "first_seen": "2026-02-09T15:19:53.688Z",
    "last_seen": "2026-02-09T21:04:02.967Z",
    "analyst_count": 1,
    "dominant_bias": "BEARISH",
    "confluence_bonus": 1
  },
  "630": {
    "level": 630,
    "count": 3,
    "analysts": {
      "mathemeatloaf7": 2,
      "kaprik0rn3": 1
    },
    "tickers": {
      "SPY": 3
    },
    "biases": {
      "BULLISH": 0,
      "BEARISH": 0,
      "NEUTRAL": 3
    },
    "signal_types": {
      "CHART_ANALYSIS": 2,
      "LEVEL_WATCH": 1
    },
    "first_seen": "2026-03-30T17:46:51.835Z",
    "last_seen": "2026-04-02T13:47:15.886Z",
    "analyst_count": 2,
    "dominant_bias": "NEUTRAL",
    "confluence_bonus": 2
  },
  "635": {
    "level": 635,
    "count": 2,
    "analysts": {
      "mathemeatloaf7": 2
    },
    "tickers": {
      "SPY": 2
    },
    "biases": {
      "BULLISH": 1,
      "BEARISH": 0,
      "NEUTRAL": 1
    },
    "signal_types": {
      "CHART_ANALYSIS": 2
    },
    "first_seen": "2026-01-29T17:04:00.739Z",
    "last_seen": "2026-04-01T13:50:34.164Z",
    "analyst_count": 1,
    "dominant_bias": "BULLISH",
    "confluence_bonus": 0
  },
  "640": {
    "level": 640,
    "count": 7,
    "analysts": {
      "mathemeatloaf7": 3,
      "kaprik0rn3": 2,
      "barrysanders329": 2
    },
    "tickers": {
      "SPY": 7
    },
    "biases": {
      "BULLISH": 0,
      "BEARISH": 0,
      "NEUTRAL": 7
    },
    "signal_types": {
      "LEVEL_WATCH": 5,
      "CHART_ANALYSIS": 2
    },
    "first_seen": "2026-03-18T17:02:17.510Z",
    "last_seen": "2026-04-01T13:44:13.228Z",
    "analyst_count": 3,
    "dominant_bias": "NEUTRAL",
    "confluence_bonus": 2
  },
  "645": {
    "level": 645,
    "count": 5,
    "analysts": {
      "mathemeatloaf7": 4,
      "kaprik0rn3": 1
    },
    "tickers": {
      "SPY": 4,
      "QQQ": 1
    },
    "biases": {
      "BULLISH": 0,
      "BEARISH": 0,
      "NEUTRAL": 5
    },
    "signal_types": {
      "LEVEL_WATCH": 5
    },
    "first_seen": "2026-03-20T19:22:09.354Z",
    "last_seen": "2026-03-31T16:38:46.784Z",
    "analyst_count": 2,
    "dominant_bias": "NEUTRAL",
    "confluence_bonus": 2
  },
  "650": {
    "level": 650,
    "count": 8,
    "analysts": {
      "kaprik0rn3": 8
    },
    "tickers": {
      "SPY": 8
    },
    "biases": {
      "BULLISH": 0,
      "BEARISH": 2,
      "NEUTRAL": 6
    },
    "signal_types": {
      "LEVEL_WATCH": 3,
      "CHART_ANALYSIS": 5
    },
    "first_seen": "2026-03-13T20:24:14.611Z",
    "last_seen": "2026-03-26T15:31:34.202Z",
    "analyst_count": 1,
    "dominant_bias": "BEARISH",
    "confluence_bonus": 2
  },
  "655": {
    "level": 655,
    "count": 4,
    "analysts": {
      "mathemeatloaf7": 3,
      "kaprik0rn3": 1
    },
    "tickers": {
      "SPY": 4
    },
    "biases": {
      "BULLISH": 0,
      "BEARISH": 1,
      "NEUTRAL": 3
    },
    "signal_types": {
      "CHART_ANALYSIS": 3,
      "LEVEL_WATCH": 1
    },
    "first_seen": "2026-03-19T17:40:07.846Z",
    "last_seen": "2026-04-01T16:58:26.337Z",
    "analyst_count": 2,
    "dominant_bias": "BEARISH",
    "confluence_bonus": 2
  },
  "660": {
    "level": 660,
    "count": 19,
    "analysts": {
      "mathemeatloaf7": 17,
      "kaprik0rn3": 2
    },
    "tickers": {
      "SPY": 17,
      "DIA": 1,
      "QQQ": 1
    },
    "biases": {
      "BULLISH": 0,
      "BEARISH": 5,
      "NEUTRAL": 14
    },
    "signal_types": {
      "LEVEL_WATCH": 12,
      "CHART_ANALYSIS": 7
    },
    "first_seen": "2026-03-12T15:16:54.591Z",
    "last_seen": "2026-04-07T17:42:08.174Z",
    "analyst_count": 2,
    "dominant_bias": "BEARISH",
    "confluence_bonus": 3
  },
  "665": {
    "level": 665,
    "count": 2,
    "analysts": {
      "mathemeatloaf7": 2
    },
    "tickers": {
      "SPY": 2
    },
    "biases": {
      "BULLISH": 0,
      "BEARISH": 1,
      "NEUTRAL": 1
    },
    "signal_types": {
      "CHART_ANALYSIS": 1,
      "LEVEL_WATCH": 1
    },
    "first_seen": "2026-03-12T20:15:47.300Z",
    "last_seen": "2026-03-18T14:27:27.561Z",
    "analyst_count": 1,
    "dominant_bias": "BEARISH",
    "confluence_bonus": 0
  },
  "670": {
    "level": 670,
    "count": 8,
    "analysts": {
      "barrysanders329": 1,
      "mathemeatloaf7": 5,
      "kaprik0rn3": 2
    },
    "tickers": {
      "SPY": 7,
      "SNDK": 1
    },
    "biases": {
      "BULLISH": 0,
      "BEARISH": 4,
      "NEUTRAL": 4
    },
    "signal_types": {
      "LEVEL_WATCH": 6,
      "CHART_ANALYSIS": 2
    },
    "first_seen": "2026-02-25T23:27:24.492Z",
    "last_seen": "2026-03-20T16:26:03.832Z",
    "analyst_count": 3,
    "dominant_bias": "BEARISH",
    "confluence_bonus": 3
  },
  "675": {
    "level": 675,
    "count": 9,
    "analysts": {
      "mathemeatloaf7": 9
    },
    "tickers": {
      "SPY": 9
    },
    "biases": {
      "BULLISH": 1,
      "BEARISH": 4,
      "NEUTRAL": 4
    },
    "signal_types": {
      "LEVEL_WATCH": 6,
      "CHART_ANALYSIS": 3
    },
    "first_seen": "2026-03-03T16:07:52.529Z",
    "last_seen": "2026-04-08T17:22:59.653Z",
    "analyst_count": 1,
    "dominant_bias": "BEARISH",
    "confluence_bonus": 2
  },
  "680": {
    "level": 680,
    "count": 18,
    "analysts": {
      "mathemeatloaf7": 18
    },
    "tickers": {
      "SPY": 17,
      "VIX": 1
    },
    "biases": {
      "BULLISH": 0,
      "BEARISH": 4,
      "NEUTRAL": 14
    },
    "signal_types": {
      "LEVEL_WATCH": 9,
      "CHART_ANALYSIS": 9
    },
    "first_seen": "2026-01-29T14:55:11.446Z",
    "last_seen": "2026-03-06T15:36:35.324Z",
    "analyst_count": 1,
    "dominant_bias": "BEARISH",
    "confluence_bonus": 2
  },
  "685": {
    "level": 685,
    "count": 10,
    "analysts": {
      "barrysanders329": 1,
      "mathemeatloaf7": 9
    },
    "tickers": {
      "SPY": 9,
      "VIX": 1
    },
    "biases": {
      "BULLISH": 0,
      "BEARISH": 4,
      "NEUTRAL": 6
    },
    "signal_types": {
      "LEVEL_WATCH": 2,
      "CHART_ANALYSIS": 8
    },
    "first_seen": "2026-01-29T14:55:11.446Z",
    "last_seen": "2026-04-17T19:00:35.944Z",
    "analyst_count": 2,
    "dominant_bias": "BEARISH",
    "confluence_bonus": 3
  },
  "690": {
    "level": 690,
    "count": 7,
    "analysts": {
      "mathemeatloaf7": 7
    },
    "tickers": {
      "QQQ": 1,
      "SPY": 6
    },
    "biases": {
      "BULLISH": 0,
      "BEARISH": 1,
      "NEUTRAL": 6
    },
    "signal_types": {
      "LEVEL_WATCH": 3,
      "CHART_ANALYSIS": 4
    },
    "first_seen": "2026-02-11T15:15:43.707Z",
    "last_seen": "2026-02-26T20:13:48.441Z",
    "analyst_count": 1,
    "dominant_bias": "BEARISH",
    "confluence_bonus": 1
  },
  "695": {
    "level": 695,
    "count": 11,
    "analysts": {
      "mathemeatloaf7": 11
    },
    "tickers": {
      "SPY": 11
    },
    "biases": {
      "BULLISH": 0,
      "BEARISH": 5,
      "NEUTRAL": 6
    },
    "signal_types": {
      "LEVEL_WATCH": 8,
      "CHART_ANALYSIS": 3
    },
    "first_seen": "2026-02-09T15:24:53.064Z",
    "last_seen": "2026-02-11T17:36:48.929Z",
    "analyst_count": 1,
    "dominant_bias": "BEARISH",
    "confluence_bonus": 2
  },
  "700": {
    "level": 700,
    "count": 4,
    "analysts": {
      "kaprik0rn3": 3,
      "mathemeatloaf7": 1
    },
    "tickers": {
      "SPY": 2,
      "APP": 1,
      "SNDK": 1
    },
    "biases": {
      "BULLISH": 2,
      "BEARISH": 0,
      "NEUTRAL": 2
    },
    "signal_types": {
      "LEVEL_WATCH": 2,
      "CHART_ANALYSIS": 2
    },
    "first_seen": "2026-01-29T17:04:00.739Z",
    "last_seen": "2026-03-27T19:55:06.189Z",
    "analyst_count": 2,
    "dominant_bias": "BULLISH",
    "confluence_bonus": 2
  },
  "715": {
    "level": 715,
    "count": 5,
    "analysts": {
      "mathemeatloaf7": 5
    },
    "tickers": {
      "SPY": 5
    },
    "biases": {
      "BULLISH": 1,
      "BEARISH": 0,
      "NEUTRAL": 4
    },
    "signal_types": {
      "CHART_ANALYSIS": 3,
      "LEVEL_WATCH": 2
    },
    "first_seen": "2026-04-08T13:46:02.905Z",
    "last_seen": "2026-04-16T19:51:49.406Z",
    "analyst_count": 1,
    "dominant_bias": "BULLISH",
    "confluence_bonus": 1
  },
  "800": {
    "level": 800,
    "count": 1,
    "analysts": {
      "mathemeatloaf7": 1
    },
    "tickers": {
      "SPY": 1
    },
    "biases": {
      "BULLISH": 0,
      "BEARISH": 0,
      "NEUTRAL": 1
    },
    "signal_types": {
      "LEVEL_WATCH": 1
    },
    "first_seen": "2026-04-17T19:45:35.368Z",
    "last_seen": "2026-04-17T19:45:35.368Z",
    "analyst_count": 1,
    "dominant_bias": "NEUTRAL",
    "confluence_bonus": 0
  },
  "885": {
    "level": 885,
    "count": 1,
    "analysts": {
      "kaprik0rn3": 1
    },
    "tickers": {
      "LLY": 1
    },
    "biases": {
      "BULLISH": 0,
      "BEARISH": 0,
      "NEUTRAL": 1
    },
    "signal_types": {
      "LEVEL_WATCH": 1
    },
    "first_seen": "2026-03-17T15:59:05.780Z",
    "last_seen": "2026-03-17T15:59:05.780Z",
    "analyst_count": 1,
    "dominant_bias": "NEUTRAL",
    "confluence_bonus": 0
  },
  "890": {
    "level": 890,
    "count": 1,
    "analysts": {
      "kaprik0rn3": 1
    },
    "tickers": {
      "LLY": 1
    },
    "biases": {
      "BULLISH": 0,
      "BEARISH": 0,
      "NEUTRAL": 1
    },
    "signal_types": {
      "LEVEL_WATCH": 1
    },
    "first_seen": "2026-04-15T16:21:38.476Z",
    "last_seen": "2026-04-15T16:21:38.476Z",
    "analyst_count": 1,
    "dominant_bias": "NEUTRAL",
    "confluence_bonus": 0
  },
  "900": {
    "level": 900,
    "count": 1,
    "analysts": {
      "kaprik0rn3": 1
    },
    "tickers": {
      "LITE": 1
    },
    "biases": {
      "BULLISH": 0,
      "BEARISH": 0,
      "NEUTRAL": 1
    },
    "signal_types": {
      "LEVEL_WATCH": 1
    },
    "first_seen": "2026-04-08T16:48:44.700Z",
    "last_seen": "2026-04-08T16:48:44.700Z",
    "analyst_count": 1,
    "dominant_bias": "NEUTRAL",
    "confluence_bonus": 0
  },
  "905": {
    "level": 905,
    "count": 1,
    "analysts": {
      "kaprik0rn3": 1
    },
    "tickers": {
      "LLY": 1
    },
    "biases": {
      "BULLISH": 0,
      "BEARISH": 0,
      "NEUTRAL": 1
    },
    "signal_types": {
      "LEVEL_WATCH": 1
    },
    "first_seen": "2026-04-15T15:57:30.778Z",
    "last_seen": "2026-04-15T15:57:30.778Z",
    "analyst_count": 1,
    "dominant_bias": "NEUTRAL",
    "confluence_bonus": 0
  },
  "965": {
    "level": 965,
    "count": 1,
    "analysts": {
      "general_dollars": 1
    },
    "tickers": {
      "SPY": 1
    },
    "biases": {
      "BULLISH": 0,
      "BEARISH": 0,
      "NEUTRAL": 1
    },
    "signal_types": {
      "LEVEL_WATCH": 1
    },
    "first_seen": "2026-03-28T04:47:33.883Z",
    "last_seen": "2026-03-28T04:47:33.883Z",
    "analyst_count": 1,
    "dominant_bias": "NEUTRAL",
    "confluence_bonus": 0
  },
  "1000": {
    "level": 1000,
    "count": 3,
    "analysts": {
      "kaprik0rn3": 2,
      "barrysanders329": 1
    },
    "tickers": {
      "CAR": 1,
      "BTC": 1,
      "LITE": 1
    },
    "biases": {
      "BULLISH": 0,
      "BEARISH": 0,
      "NEUTRAL": 3
    },
    "signal_types": {
      "LEVEL_WATCH": 2,
      "CHART_ANALYSIS": 1
    },
    "first_seen": "2026-04-08T14:30:23.052Z",
    "last_seen": "2026-04-21T17:54:44.463Z",
    "analyst_count": 2,
    "dominant_bias": "NEUTRAL",
    "confluence_bonus": 2
  },
  "2015": {
    "level": 2015,
    "count": 1,
    "analysts": {
      "barrysanders329": 1
    },
    "tickers": {
      "QQQ": 1
    },
    "biases": {
      "BULLISH": 0,
      "BEARISH": 0,
      "NEUTRAL": 1
    },
    "signal_types": {
      "CHART_ANALYSIS": 1
    },
    "first_seen": "2026-02-14T04:48:19.516Z",
    "last_seen": "2026-02-14T04:48:19.516Z",
    "analyst_count": 1,
    "dominant_bias": "NEUTRAL",
    "confluence_bonus": 0
  },
  "2020": {
    "level": 2020,
    "count": 1,
    "analysts": {
      "barrysanders329": 1
    },
    "tickers": {
      "QQQ": 1
    },
    "biases": {
      "BULLISH": 0,
      "BEARISH": 0,
      "NEUTRAL": 1
    },
    "signal_types": {
      "CHART_ANALYSIS": 1
    },
    "first_seen": "2026-02-14T04:48:19.516Z",
    "last_seen": "2026-02-14T04:48:19.516Z",
    "analyst_count": 1,
    "dominant_bias": "NEUTRAL",
    "confluence_bonus": 0
  },
  "3300": {
    "level": 3300,
    "count": 2,
    "analysts": {
      "mathemeatloaf7": 2
    },
    "tickers": {
      "SPX": 2
    },
    "biases": {
      "BULLISH": 0,
      "BEARISH": 0,
      "NEUTRAL": 2
    },
    "signal_types": {
      "LEVEL_WATCH": 2
    },
    "first_seen": "2026-03-12T15:57:06.554Z",
    "last_seen": "2026-03-13T16:01:12.451Z",
    "analyst_count": 1,
    "dominant_bias": "NEUTRAL",
    "confluence_bonus": 0
  },
  "3800": {
    "level": 3800,
    "count": 1,
    "analysts": {
      "mathemeatloaf7": 1
    },
    "tickers": {
      "SPX": 1
    },
    "biases": {
      "BULLISH": 0,
      "BEARISH": 0,
      "NEUTRAL": 1
    },
    "signal_types": {
      "LEVEL_WATCH": 1
    },
    "first_seen": "2026-03-26T18:36:29.511Z",
    "last_seen": "2026-03-26T18:36:29.511Z",
    "analyst_count": 1,
    "dominant_bias": "NEUTRAL",
    "confluence_bonus": 0
  },
  "4100": {
    "level": 4100,
    "count": 1,
    "analysts": {
      "kaprik0rn3": 1
    },
    "tickers": {
      "LOD": 1
    },
    "biases": {
      "BULLISH": 0,
      "BEARISH": 0,
      "NEUTRAL": 1
    },
    "signal_types": {
      "LEVEL_WATCH": 1
    },
    "first_seen": "2026-03-23T11:25:34.986Z",
    "last_seen": "2026-03-23T11:25:34.986Z",
    "analyst_count": 1,
    "dominant_bias": "NEUTRAL",
    "confluence_bonus": 0
  },
  "4300": {
    "level": 4300,
    "count": 4,
    "analysts": {
      "mathemeatloaf7": 4
    },
    "tickers": {
      "SPX": 4
    },
    "biases": {
      "BULLISH": 0,
      "BEARISH": 0,
      "NEUTRAL": 4
    },
    "signal_types": {
      "LEVEL_WATCH": 4
    },
    "first_seen": "2026-03-12T15:23:25.612Z",
    "last_seen": "2026-03-26T19:34:44.305Z",
    "analyst_count": 1,
    "dominant_bias": "NEUTRAL",
    "confluence_bonus": 1
  },
  "5300": {
    "level": 5300,
    "count": 6,
    "analysts": {
      "mathemeatloaf7": 6
    },
    "tickers": {
      "SPX": 6
    },
    "biases": {
      "BULLISH": 0,
      "BEARISH": 0,
      "NEUTRAL": 6
    },
    "signal_types": {
      "LEVEL_WATCH": 5,
      "CHART_ANALYSIS": 1
    },
    "first_seen": "2026-03-10T18:17:52.400Z",
    "last_seen": "2026-03-23T20:04:13.074Z",
    "analyst_count": 1,
    "dominant_bias": "NEUTRAL",
    "confluence_bonus": 1
  },
  "5600": {
    "level": 5600,
    "count": 1,
    "analysts": {
      "mathemeatloaf7": 1
    },
    "tickers": {
      "SPX": 1
    },
    "biases": {
      "BULLISH": 0,
      "BEARISH": 0,
      "NEUTRAL": 1
    },
    "signal_types": {
      "CHART_ANALYSIS": 1
    },
    "first_seen": "2026-03-19T17:07:36.158Z",
    "last_seen": "2026-03-19T17:07:36.158Z",
    "analyst_count": 1,
    "dominant_bias": "NEUTRAL",
    "confluence_bonus": 0
  },
  "5900": {
    "level": 5900,
    "count": 1,
    "analysts": {
      "mathemeatloaf7": 1
    },
    "tickers": {
      "SPX": 1
    },
    "biases": {
      "BULLISH": 0,
      "BEARISH": 0,
      "NEUTRAL": 1
    },
    "signal_types": {
      "CHART_ANALYSIS": 1
    },
    "first_seen": "2026-03-19T17:07:36.158Z",
    "last_seen": "2026-03-19T17:07:36.158Z",
    "analyst_count": 1,
    "dominant_bias": "NEUTRAL",
    "confluence_bonus": 0
  },
  "6100": {
    "level": 6100,
    "count": 1,
    "analysts": {
      "mathemeatloaf7": 1
    },
    "tickers": {
      "SPX": 1
    },
    "biases": {
      "BULLISH": 0,
      "BEARISH": 0,
      "NEUTRAL": 1
    },
    "signal_types": {
      "LEVEL_WATCH": 1
    },
    "first_seen": "2026-03-13T18:14:28.037Z",
    "last_seen": "2026-03-13T18:14:28.037Z",
    "analyst_count": 1,
    "dominant_bias": "NEUTRAL",
    "confluence_bonus": 0
  },
  "6320": {
    "level": 6320,
    "count": 1,
    "analysts": {
      "mathemeatloaf7": 1
    },
    "tickers": {
      "SPX": 1
    },
    "biases": {
      "BULLISH": 0,
      "BEARISH": 0,
      "NEUTRAL": 1
    },
    "signal_types": {
      "CHART_ANALYSIS": 1
    },
    "first_seen": "2026-04-02T13:44:56.284Z",
    "last_seen": "2026-04-02T13:44:56.284Z",
    "analyst_count": 1,
    "dominant_bias": "NEUTRAL",
    "confluence_bonus": 0
  },
  "6340": {
    "level": 6340,
    "count": 1,
    "analysts": {
      "mathemeatloaf7": 1
    },
    "tickers": {
      "SPX": 1
    },
    "biases": {
      "BULLISH": 0,
      "BEARISH": 1,
      "NEUTRAL": 0
    },
    "signal_types": {
      "CHART_ANALYSIS": 1
    },
    "first_seen": "2026-03-30T14:00:11.874Z",
    "last_seen": "2026-03-30T14:00:11.874Z",
    "analyst_count": 1,
    "dominant_bias": "BEARISH",
    "confluence_bonus": 0
  },
  "6350": {
    "level": 6350,
    "count": 1,
    "analysts": {
      "mathemeatloaf7": 1
    },
    "tickers": {
      "SPX": 1
    },
    "biases": {
      "BULLISH": 0,
      "BEARISH": 1,
      "NEUTRAL": 0
    },
    "signal_types": {
      "CHART_ANALYSIS": 1
    },
    "first_seen": "2026-03-30T14:00:11.874Z",
    "last_seen": "2026-03-30T14:00:11.874Z",
    "analyst_count": 1,
    "dominant_bias": "BEARISH",
    "confluence_bonus": 0
  },
  "6460": {
    "level": 6460,
    "count": 1,
    "analysts": {
      "kaprik0rn3": 1
    },
    "tickers": {
      "SPX": 1
    },
    "biases": {
      "BULLISH": 0,
      "BEARISH": 0,
      "NEUTRAL": 1
    },
    "signal_types": {
      "LEVEL_WATCH": 1
    },
    "first_seen": "2026-03-26T19:14:16.279Z",
    "last_seen": "2026-03-26T19:14:16.279Z",
    "analyst_count": 1,
    "dominant_bias": "NEUTRAL",
    "confluence_bonus": 0
  },
  "6475": {
    "level": 6475,
    "count": 1,
    "analysts": {
      "mathemeatloaf7": 1
    },
    "tickers": {
      "SPX": 1
    },
    "biases": {
      "BULLISH": 0,
      "BEARISH": 0,
      "NEUTRAL": 1
    },
    "signal_types": {
      "CHART_ANALYSIS": 1
    },
    "first_seen": "2026-03-24T13:38:01.759Z",
    "last_seen": "2026-03-24T13:38:01.759Z",
    "analyst_count": 1,
    "dominant_bias": "NEUTRAL",
    "confluence_bonus": 0
  },
  "6500": {
    "level": 6500,
    "count": 2,
    "analysts": {
      "mathemeatloaf7": 1,
      "kaprik0rn3": 1
    },
    "tickers": {
      "SPX": 1,
      "VIX": 1
    },
    "biases": {
      "BULLISH": 0,
      "BEARISH": 1,
      "NEUTRAL": 1
    },
    "signal_types": {
      "LEVEL_WATCH": 2
    },
    "first_seen": "2026-03-08T23:39:23.967Z",
    "last_seen": "2026-04-21T18:41:18.299Z",
    "analyst_count": 2,
    "dominant_bias": "BEARISH",
    "confluence_bonus": 1
  },
  "6530": {
    "level": 6530,
    "count": 1,
    "analysts": {
      "mathemeatloaf7": 1
    },
    "tickers": {
      "SPY": 1
    },
    "biases": {
      "BULLISH": 0,
      "BEARISH": 0,
      "NEUTRAL": 1
    },
    "signal_types": {
      "LEVEL_WATCH": 1
    },
    "first_seen": "2026-04-01T14:42:22.588Z",
    "last_seen": "2026-04-01T14:42:22.588Z",
    "analyst_count": 1,
    "dominant_bias": "NEUTRAL",
    "confluence_bonus": 0
  },
  "6550": {
    "level": 6550,
    "count": 1,
    "analysts": {
      "kaprik0rn3": 1
    },
    "tickers": {
      "SPX": 1
    },
    "biases": {
      "BULLISH": 0,
      "BEARISH": 0,
      "NEUTRAL": 1
    },
    "signal_types": {
      "LEVEL_WATCH": 1
    },
    "first_seen": "2026-03-19T18:34:43.269Z",
    "last_seen": "2026-03-19T18:34:43.269Z",
    "analyst_count": 1,
    "dominant_bias": "NEUTRAL",
    "confluence_bonus": 0
  },
  "6555": {
    "level": 6555,
    "count": 1,
    "analysts": {
      "barrysanders329": 1
    },
    "tickers": {
      "SPX": 1
    },
    "biases": {
      "BULLISH": 0,
      "BEARISH": 0,
      "NEUTRAL": 1
    },
    "signal_types": {
      "LEVEL_WATCH": 1
    },
    "first_seen": "2026-04-01T14:34:18.704Z",
    "last_seen": "2026-04-01T14:34:18.704Z",
    "analyst_count": 1,
    "dominant_bias": "NEUTRAL",
    "confluence_bonus": 0
  },
  "6570": {
    "level": 6570,
    "count": 1,
    "analysts": {
      "barrysanders329": 1
    },
    "tickers": {
      "SPX": 1
    },
    "biases": {
      "BULLISH": 0,
      "BEARISH": 0,
      "NEUTRAL": 1
    },
    "signal_types": {
      "LEVEL_WATCH": 1
    },
    "first_seen": "2026-03-31T17:13:34.749Z",
    "last_seen": "2026-03-31T17:13:34.749Z",
    "analyst_count": 1,
    "dominant_bias": "NEUTRAL",
    "confluence_bonus": 0
  },
  "6585": {
    "level": 6585,
    "count": 1,
    "analysts": {
      "barrysanders329": 1
    },
    "tickers": {
      "SPX": 1
    },
    "biases": {
      "BULLISH": 0,
      "BEARISH": 0,
      "NEUTRAL": 1
    },
    "signal_types": {
      "LEVEL_WATCH": 1
    },
    "first_seen": "2026-04-01T14:34:18.704Z",
    "last_seen": "2026-04-01T14:34:18.704Z",
    "analyst_count": 1,
    "dominant_bias": "NEUTRAL",
    "confluence_bonus": 0
  },
  "6600": {
    "level": 6600,
    "count": 1,
    "analysts": {
      "mathemeatloaf7": 1
    },
    "tickers": {
      "SPX": 1
    },
    "biases": {
      "BULLISH": 0,
      "BEARISH": 0,
      "NEUTRAL": 1
    },
    "signal_types": {
      "LEVEL_WATCH": 1
    },
    "first_seen": "2026-03-24T15:25:42.611Z",
    "last_seen": "2026-03-24T15:25:42.611Z",
    "analyst_count": 1,
    "dominant_bias": "NEUTRAL",
    "confluence_bonus": 0
  },
  "6615": {
    "level": 6615,
    "count": 1,
    "analysts": {
      "mathemeatloaf7": 1
    },
    "tickers": {
      "SPX": 1
    },
    "biases": {
      "BULLISH": 0,
      "BEARISH": 1,
      "NEUTRAL": 0
    },
    "signal_types": {
      "LEVEL_WATCH": 1
    },
    "first_seen": "2026-03-18T18:59:18.685Z",
    "last_seen": "2026-03-18T18:59:18.685Z",
    "analyst_count": 1,
    "dominant_bias": "BEARISH",
    "confluence_bonus": 0
  },
  "6620": {
    "level": 6620,
    "count": 2,
    "analysts": {
      "mathemeatloaf7": 1,
      "barrysanders329": 1
    },
    "tickers": {
      "SPX": 2
    },
    "biases": {
      "BULLISH": 0,
      "BEARISH": 0,
      "NEUTRAL": 2
    },
    "signal_types": {
      "LEVEL_WATCH": 2
    },
    "first_seen": "2026-03-13T15:43:38.426Z",
    "last_seen": "2026-03-16T14:40:49.971Z",
    "analyst_count": 2,
    "dominant_bias": "NEUTRAL",
    "confluence_bonus": 1
  },
  "6640": {
    "level": 6640,
    "count": 2,
    "analysts": {
      "mathemeatloaf7": 1,
      "barrysanders329": 1
    },
    "tickers": {
      "SPX": 2
    },
    "biases": {
      "BULLISH": 0,
      "BEARISH": 1,
      "NEUTRAL": 1
    },
    "signal_types": {
      "LEVEL_WATCH": 2
    },
    "first_seen": "2026-03-13T14:51:38.265Z",
    "last_seen": "2026-03-18T18:59:18.685Z",
    "analyst_count": 2,
    "dominant_bias": "BEARISH",
    "confluence_bonus": 1
  },
  "6650": {
    "level": 6650,
    "count": 6,
    "analysts": {
      "kaprik0rn3": 3,
      "mathemeatloaf7": 3
    },
    "tickers": {
      "LIS": 1,
      "SPX": 5
    },
    "biases": {
      "BULLISH": 0,
      "BEARISH": 0,
      "NEUTRAL": 6
    },
    "signal_types": {
      "LEVEL_WATCH": 5,
      "CHART_ANALYSIS": 1
    },
    "first_seen": "2026-03-12T18:49:23.185Z",
    "last_seen": "2026-03-25T14:33:19.375Z",
    "analyst_count": 2,
    "dominant_bias": "NEUTRAL",
    "confluence_bonus": 2
  },
  "6660": {
    "level": 6660,
    "count": 1,
    "analysts": {
      "mathemeatloaf7": 1
    },
    "tickers": {
      "SPX": 1
    },
    "biases": {
      "BULLISH": 0,
      "BEARISH": 0,
      "NEUTRAL": 1
    },
    "signal_types": {
      "LEVEL_WATCH": 1
    },
    "first_seen": "2026-03-16T14:34:02.449Z",
    "last_seen": "2026-03-16T14:34:02.449Z",
    "analyst_count": 1,
    "dominant_bias": "NEUTRAL",
    "confluence_bonus": 0
  },
  "6675": {
    "level": 6675,
    "count": 1,
    "analysts": {
      "mathemeatloaf7": 1
    },
    "tickers": {
      "SPX": 1
    },
    "biases": {
      "BULLISH": 0,
      "BEARISH": 0,
      "NEUTRAL": 1
    },
    "signal_types": {
      "LEVEL_WATCH": 1
    },
    "first_seen": "2026-03-03T15:24:24.365Z",
    "last_seen": "2026-03-03T15:24:24.365Z",
    "analyst_count": 1,
    "dominant_bias": "NEUTRAL",
    "confluence_bonus": 0
  },
  "6680": {
    "level": 6680,
    "count": 1,
    "analysts": {
      "mathemeatloaf7": 1
    },
    "tickers": {
      "VIX": 1
    },
    "biases": {
      "BULLISH": 0,
      "BEARISH": 0,
      "NEUTRAL": 1
    },
    "signal_types": {
      "CHART_ANALYSIS": 1
    },
    "first_seen": "2026-03-06T15:15:27.405Z",
    "last_seen": "2026-03-06T15:15:27.405Z",
    "analyst_count": 1,
    "dominant_bias": "NEUTRAL",
    "confluence_bonus": 0
  },
  "6700": {
    "level": 6700,
    "count": 4,
    "analysts": {
      "mathemeatloaf7": 4
    },
    "tickers": {
      "SPX": 4
    },
    "biases": {
      "BULLISH": 0,
      "BEARISH": 0,
      "NEUTRAL": 4
    },
    "signal_types": {
      "LEVEL_WATCH": 4
    },
    "first_seen": "2026-03-03T15:24:06.408Z",
    "last_seen": "2026-04-21T18:41:18.299Z",
    "analyst_count": 1,
    "dominant_bias": "NEUTRAL",
    "confluence_bonus": 1
  },
  "6705": {
    "level": 6705,
    "count": 2,
    "analysts": {
      "mathemeatloaf7": 2
    },
    "tickers": {
      "SPX": 2
    },
    "biases": {
      "BULLISH": 0,
      "BEARISH": 0,
      "NEUTRAL": 2
    },
    "signal_types": {
      "LEVEL_WATCH": 2
    },
    "first_seen": "2026-03-03T15:24:06.408Z",
    "last_seen": "2026-03-03T15:38:00.947Z",
    "analyst_count": 1,
    "dominant_bias": "NEUTRAL",
    "confluence_bonus": 0
  },
  "6730": {
    "level": 6730,
    "count": 1,
    "analysts": {
      "kaprik0rn3": 1
    },
    "tickers": {
      "SPX": 1
    },
    "biases": {
      "BULLISH": 0,
      "BEARISH": 0,
      "NEUTRAL": 1
    },
    "signal_types": {
      "LEVEL_WATCH": 1
    },
    "first_seen": "2026-03-16T14:09:35.723Z",
    "last_seen": "2026-03-16T14:09:35.723Z",
    "analyst_count": 1,
    "dominant_bias": "NEUTRAL",
    "confluence_bonus": 0
  },
  "6740": {
    "level": 6740,
    "count": 2,
    "analysts": {
      "mathemeatloaf7": 2
    },
    "tickers": {
      "SPX": 2
    },
    "biases": {
      "BULLISH": 0,
      "BEARISH": 0,
      "NEUTRAL": 2
    },
    "signal_types": {
      "LEVEL_WATCH": 2
    },
    "first_seen": "2026-04-09T14:06:09.415Z",
    "last_seen": "2026-04-09T14:42:19.028Z",
    "analyst_count": 1,
    "dominant_bias": "NEUTRAL",
    "confluence_bonus": 0
  },
  "6760": {
    "level": 6760,
    "count": 2,
    "analysts": {
      "mathemeatloaf7": 2
    },
    "tickers": {
      "SPX": 2
    },
    "biases": {
      "BULLISH": 0,
      "BEARISH": 1,
      "NEUTRAL": 1
    },
    "signal_types": {
      "LEVEL_WATCH": 1,
      "CHART_ANALYSIS": 1
    },
    "first_seen": "2026-02-17T14:47:41.463Z",
    "last_seen": "2026-03-17T13:40:10.419Z",
    "analyst_count": 1,
    "dominant_bias": "BEARISH",
    "confluence_bonus": 0
  },
  "6770": {
    "level": 6770,
    "count": 1,
    "analysts": {
      "mathemeatloaf7": 1
    },
    "tickers": {
      "SPX": 1
    },
    "biases": {
      "BULLISH": 0,
      "BEARISH": 1,
      "NEUTRAL": 0
    },
    "signal_types": {
      "CHART_ANALYSIS": 1
    },
    "first_seen": "2026-02-17T14:47:41.463Z",
    "last_seen": "2026-02-17T14:47:41.463Z",
    "analyst_count": 1,
    "dominant_bias": "BEARISH",
    "confluence_bonus": 0
  },
  "6780": {
    "level": 6780,
    "count": 3,
    "analysts": {
      "mathemeatloaf7": 3
    },
    "tickers": {
      "SPX": 1,
      "SPY": 2
    },
    "biases": {
      "BULLISH": 0,
      "BEARISH": 1,
      "NEUTRAL": 2
    },
    "signal_types": {
      "LEVEL_WATCH": 2,
      "CHART_ANALYSIS": 1
    },
    "first_seen": "2026-03-05T17:30:57.507Z",
    "last_seen": "2026-03-05T18:24:12.507Z",
    "analyst_count": 1,
    "dominant_bias": "BEARISH",
    "confluence_bonus": 1
  },
  "6785": {
    "level": 6785,
    "count": 1,
    "analysts": {
      "barrysanders329": 1
    },
    "tickers": {
      "SPX": 1
    },
    "biases": {
      "BULLISH": 0,
      "BEARISH": 0,
      "NEUTRAL": 1
    },
    "signal_types": {
      "LEVEL_WATCH": 1
    },
    "first_seen": "2026-04-08T17:00:00.055Z",
    "last_seen": "2026-04-08T17:00:00.055Z",
    "analyst_count": 1,
    "dominant_bias": "NEUTRAL",
    "confluence_bonus": 0
  },
  "6790": {
    "level": 6790,
    "count": 4,
    "analysts": {
      "kaprik0rn3": 1,
      "mathemeatloaf7": 3
    },
    "tickers": {
      "SPX": 2,
      "SPY": 2
    },
    "biases": {
      "BULLISH": 0,
      "BEARISH": 1,
      "NEUTRAL": 3
    },
    "signal_types": {
      "LEVEL_WATCH": 2,
      "CHART_ANALYSIS": 2
    },
    "first_seen": "2026-03-03T16:21:25.183Z",
    "last_seen": "2026-03-05T17:30:43.956Z",
    "analyst_count": 2,
    "dominant_bias": "BEARISH",
    "confluence_bonus": 2
  },
  "6800": {
    "level": 6800,
    "count": 5,
    "analysts": {
      "mathemeatloaf7": 3,
      "barrysanders329": 1,
      "kaprik0rn3": 1
    },
    "tickers": {
      "SPX": 3,
      "SPY": 2
    },
    "biases": {
      "BULLISH": 0,
      "BEARISH": 2,
      "NEUTRAL": 3
    },
    "signal_types": {
      "LEVEL_WATCH": 3,
      "CHART_ANALYSIS": 2
    },
    "first_seen": "2026-02-23T20:00:44.447Z",
    "last_seen": "2026-04-21T15:56:11.475Z",
    "analyst_count": 3,
    "dominant_bias": "BEARISH",
    "confluence_bonus": 2
  },
  "6815": {
    "level": 6815,
    "count": 1,
    "analysts": {
      "barrysanders329": 1
    },
    "tickers": {
      "SPX": 1
    },
    "biases": {
      "BULLISH": 0,
      "BEARISH": 0,
      "NEUTRAL": 1
    },
    "signal_types": {
      "LEVEL_WATCH": 1
    },
    "first_seen": "2026-04-08T17:00:00.055Z",
    "last_seen": "2026-04-08T17:00:00.055Z",
    "analyst_count": 1,
    "dominant_bias": "NEUTRAL",
    "confluence_bonus": 0
  },
  "6850": {
    "level": 6850,
    "count": 2,
    "analysts": {
      "mathemeatloaf7": 1,
      "kaprik0rn3": 1
    },
    "tickers": {
      "SPX": 2
    },
    "biases": {
      "BULLISH": 0,
      "BEARISH": 1,
      "NEUTRAL": 1
    },
    "signal_types": {
      "LEVEL_WATCH": 2
    },
    "first_seen": "2026-02-23T20:00:44.447Z",
    "last_seen": "2026-02-24T16:01:38.387Z",
    "analyst_count": 2,
    "dominant_bias": "BEARISH",
    "confluence_bonus": 1
  },
  "6865": {
    "level": 6865,
    "count": 6,
    "analysts": {
      "kaprik0rn3": 1,
      "mathemeatloaf7": 5
    },
    "tickers": {
      "VIX": 1,
      "SPX": 5
    },
    "biases": {
      "BULLISH": 0,
      "BEARISH": 0,
      "NEUTRAL": 6
    },
    "signal_types": {
      "LEVEL_WATCH": 2,
      "CHART_ANALYSIS": 4
    },
    "first_seen": "2026-02-17T17:09:19.609Z",
    "last_seen": "2026-03-10T17:06:25.345Z",
    "analyst_count": 2,
    "dominant_bias": "NEUTRAL",
    "confluence_bonus": 2
  },
  "6870": {
    "level": 6870,
    "count": 1,
    "analysts": {
      "mathemeatloaf7": 1
    },
    "tickers": {
      "SPX": 1
    },
    "biases": {
      "BULLISH": 0,
      "BEARISH": 0,
      "NEUTRAL": 1
    },
    "signal_types": {
      "LEVEL_WATCH": 1
    },
    "first_seen": "2026-02-18T14:49:22.148Z",
    "last_seen": "2026-02-18T14:49:22.148Z",
    "analyst_count": 1,
    "dominant_bias": "NEUTRAL",
    "confluence_bonus": 0
  },
  "6875": {
    "level": 6875,
    "count": 6,
    "analysts": {
      "mathemeatloaf7": 5,
      "barrysanders329": 1
    },
    "tickers": {
      "SPX": 6
    },
    "biases": {
      "BULLISH": 0,
      "BEARISH": 3,
      "NEUTRAL": 3
    },
    "signal_types": {
      "CHART_ANALYSIS": 2,
      "LEVEL_WATCH": 4
    },
    "first_seen": "2026-02-12T15:56:15.816Z",
    "last_seen": "2026-02-23T15:17:57.230Z",
    "analyst_count": 2,
    "dominant_bias": "BEARISH",
    "confluence_bonus": 2
  },
  "6885": {
    "level": 6885,
    "count": 2,
    "analysts": {
      "mathemeatloaf7": 2
    },
    "tickers": {
      "SPX": 2
    },
    "biases": {
      "BULLISH": 0,
      "BEARISH": 0,
      "NEUTRAL": 2
    },
    "signal_types": {
      "LEVEL_WATCH": 2
    },
    "first_seen": "2026-04-20T14:45:54.138Z",
    "last_seen": "2026-04-20T14:57:37.590Z",
    "analyst_count": 1,
    "dominant_bias": "NEUTRAL",
    "confluence_bonus": 0
  },
  "6890": {
    "level": 6890,
    "count": 2,
    "analysts": {
      "mathemeatloaf7": 2
    },
    "tickers": {
      "SPX": 2
    },
    "biases": {
      "BULLISH": 0,
      "BEARISH": 0,
      "NEUTRAL": 2
    },
    "signal_types": {
      "LEVEL_WATCH": 1,
      "CHART_ANALYSIS": 1
    },
    "first_seen": "2026-02-13T17:09:50.363Z",
    "last_seen": "2026-04-21T15:56:11.475Z",
    "analyst_count": 1,
    "dominant_bias": "NEUTRAL",
    "confluence_bonus": 0
  },
  "6900": {
    "level": 6900,
    "count": 9,
    "analysts": {
      "kaprik0rn3": 5,
      "mathemeatloaf7": 4
    },
    "tickers": {
      "SPX": 7,
      "SPY": 2
    },
    "biases": {
      "BULLISH": 0,
      "BEARISH": 1,
      "NEUTRAL": 8
    },
    "signal_types": {
      "LEVEL_WATCH": 6,
      "CHART_ANALYSIS": 3
    },
    "first_seen": "2026-02-11T15:15:43.707Z",
    "last_seen": "2026-03-04T19:24:39.103Z",
    "analyst_count": 2,
    "dominant_bias": "BEARISH",
    "confluence_bonus": 3
  },
  "6905": {
    "level": 6905,
    "count": 2,
    "analysts": {
      "mathemeatloaf7": 2
    },
    "tickers": {
      "SPX": 1,
      "SPY": 1
    },
    "biases": {
      "BULLISH": 0,
      "BEARISH": 0,
      "NEUTRAL": 2
    },
    "signal_types": {
      "CHART_ANALYSIS": 2
    },
    "first_seen": "2026-02-18T17:58:21.693Z",
    "last_seen": "2026-03-04T15:29:49.571Z",
    "analyst_count": 1,
    "dominant_bias": "NEUTRAL",
    "confluence_bonus": 0
  },
  "6920": {
    "level": 6920,
    "count": 1,
    "analysts": {
      "kaprik0rn3": 1
    },
    "tickers": {
      "SPX": 1
    },
    "biases": {
      "BULLISH": 0,
      "BEARISH": 0,
      "NEUTRAL": 1
    },
    "signal_types": {
      "LEVEL_WATCH": 1
    },
    "first_seen": "2026-02-20T19:54:54.599Z",
    "last_seen": "2026-02-20T19:54:54.599Z",
    "analyst_count": 1,
    "dominant_bias": "NEUTRAL",
    "confluence_bonus": 0
  },
  "6925": {
    "level": 6925,
    "count": 2,
    "analysts": {
      "mathemeatloaf7": 2
    },
    "tickers": {
      "SPY": 1,
      "SPX": 1
    },
    "biases": {
      "BULLISH": 0,
      "BEARISH": 0,
      "NEUTRAL": 2
    },
    "signal_types": {
      "CHART_ANALYSIS": 2
    },
    "first_seen": "2026-02-18T16:27:27.774Z",
    "last_seen": "2026-02-18T18:02:27.862Z",
    "analyst_count": 1,
    "dominant_bias": "NEUTRAL",
    "confluence_bonus": 0
  },
  "6930": {
    "level": 6930,
    "count": 1,
    "analysts": {
      "kaprik0rn3": 1
    },
    "tickers": {
      "SPX": 1
    },
    "biases": {
      "BULLISH": 0,
      "BEARISH": 0,
      "NEUTRAL": 1
    },
    "signal_types": {
      "LEVEL_WATCH": 1
    },
    "first_seen": "2026-02-10T18:49:53.244Z",
    "last_seen": "2026-02-10T18:49:53.244Z",
    "analyst_count": 1,
    "dominant_bias": "NEUTRAL",
    "confluence_bonus": 0
  },
  "6945": {
    "level": 6945,
    "count": 3,
    "analysts": {
      "mathemeatloaf7": 3
    },
    "tickers": {
      "SPX": 3
    },
    "biases": {
      "BULLISH": 0,
      "BEARISH": 2,
      "NEUTRAL": 1
    },
    "signal_types": {
      "LEVEL_WATCH": 2,
      "CHART_ANALYSIS": 1
    },
    "first_seen": "2026-02-25T17:21:48.417Z",
    "last_seen": "2026-02-25T17:53:49.920Z",
    "analyst_count": 1,
    "dominant_bias": "BEARISH",
    "confluence_bonus": 1
  },
  "6950": {
    "level": 6950,
    "count": 9,
    "analysts": {
      "kaprik0rn3": 3,
      "mathemeatloaf7": 6
    },
    "tickers": {
      "VIX": 1,
      "SPX": 8
    },
    "biases": {
      "BULLISH": 0,
      "BEARISH": 5,
      "NEUTRAL": 4
    },
    "signal_types": {
      "LEVEL_WATCH": 8,
      "CHART_ANALYSIS": 1
    },
    "first_seen": "2026-02-11T17:24:27.614Z",
    "last_seen": "2026-02-25T19:52:32.262Z",
    "analyst_count": 2,
    "dominant_bias": "BEARISH",
    "confluence_bonus": 3
  },
  "6970": {
    "level": 6970,
    "count": 3,
    "analysts": {
      "mathemeatloaf7": 3
    },
    "tickers": {
      "SPX": 3
    },
    "biases": {
      "BULLISH": 0,
      "BEARISH": 1,
      "NEUTRAL": 2
    },
    "signal_types": {
      "LEVEL_WATCH": 1,
      "CHART_ANALYSIS": 2
    },
    "first_seen": "2026-02-09T19:05:56.094Z",
    "last_seen": "2026-02-10T20:04:32.311Z",
    "analyst_count": 1,
    "dominant_bias": "BEARISH",
    "confluence_bonus": 1
  },
  "6980": {
    "level": 6980,
    "count": 4,
    "analysts": {
      "mathemeatloaf7": 4
    },
    "tickers": {
      "SPX": 1,
      "SPY": 3
    },
    "biases": {
      "BULLISH": 0,
      "BEARISH": 3,
      "NEUTRAL": 1
    },
    "signal_types": {
      "CHART_ANALYSIS": 3,
      "LEVEL_WATCH": 1
    },
    "first_seen": "2026-02-09T16:57:42.905Z",
    "last_seen": "2026-02-11T17:36:48.929Z",
    "analyst_count": 1,
    "dominant_bias": "BEARISH",
    "confluence_bonus": 1
  },
  "7000": {
    "level": 7000,
    "count": 3,
    "analysts": {
      "kaprik0rn3": 2,
      "mathemeatloaf7": 1
    },
    "tickers": {
      "SPX": 2,
      "SPY": 1
    },
    "biases": {
      "BULLISH": 0,
      "BEARISH": 0,
      "NEUTRAL": 3
    },
    "signal_types": {
      "LEVEL_WATCH": 3
    },
    "first_seen": "2026-02-09T15:24:53.064Z",
    "last_seen": "2026-04-14T16:27:23.160Z",
    "analyst_count": 2,
    "dominant_bias": "NEUTRAL",
    "confluence_bonus": 2
  },
  "7010": {
    "level": 7010,
    "count": 3,
    "analysts": {
      "mathemeatloaf7": 3
    },
    "tickers": {
      "SPX": 3
    },
    "biases": {
      "BULLISH": 0,
      "BEARISH": 2,
      "NEUTRAL": 1
    },
    "signal_types": {
      "LEVEL_WATCH": 1,
      "CHART_ANALYSIS": 2
    },
    "first_seen": "2026-02-09T15:37:18.629Z",
    "last_seen": "2026-02-10T15:31:44.842Z",
    "analyst_count": 1,
    "dominant_bias": "BEARISH",
    "confluence_bonus": 1
  },
  "7015": {
    "level": 7015,
    "count": 1,
    "analysts": {
      "mathemeatloaf7": 1
    },
    "tickers": {
      "SPX": 1
    },
    "biases": {
      "BULLISH": 0,
      "BEARISH": 1,
      "NEUTRAL": 0
    },
    "signal_types": {
      "CHART_ANALYSIS": 1
    },
    "first_seen": "2026-02-09T15:37:18.629Z",
    "last_seen": "2026-02-09T15:37:18.629Z",
    "analyst_count": 1,
    "dominant_bias": "BEARISH",
    "confluence_bonus": 0
  },
  "7040": {
    "level": 7040,
    "count": 1,
    "analysts": {
      "mathemeatloaf7": 1
    },
    "tickers": {
      "SPX": 1
    },
    "biases": {
      "BULLISH": 0,
      "BEARISH": 0,
      "NEUTRAL": 1
    },
    "signal_types": {
      "LEVEL_WATCH": 1
    },
    "first_seen": "2026-04-20T14:57:37.590Z",
    "last_seen": "2026-04-20T14:57:37.590Z",
    "analyst_count": 1,
    "dominant_bias": "NEUTRAL",
    "confluence_bonus": 0
  },
  "7050": {
    "level": 7050,
    "count": 1,
    "analysts": {
      "mathemeatloaf7": 1
    },
    "tickers": {
      "SPX": 1
    },
    "biases": {
      "BULLISH": 0,
      "BEARISH": 0,
      "NEUTRAL": 1
    },
    "signal_types": {
      "CHART_ANALYSIS": 1
    },
    "first_seen": "2026-04-20T15:07:28.245Z",
    "last_seen": "2026-04-20T15:07:28.245Z",
    "analyst_count": 1,
    "dominant_bias": "NEUTRAL",
    "confluence_bonus": 0
  },
  "7065": {
    "level": 7065,
    "count": 2,
    "analysts": {
      "mathemeatloaf7": 2
    },
    "tickers": {
      "SPX": 2
    },
    "biases": {
      "BULLISH": 0,
      "BEARISH": 0,
      "NEUTRAL": 2
    },
    "signal_types": {
      "CHART_ANALYSIS": 2
    },
    "first_seen": "2026-04-21T18:16:54.312Z",
    "last_seen": "2026-04-21T19:51:25.798Z",
    "analyst_count": 1,
    "dominant_bias": "NEUTRAL",
    "confluence_bonus": 0
  },
  "7070": {
    "level": 7070,
    "count": 2,
    "analysts": {
      "mathemeatloaf7": 2
    },
    "tickers": {
      "SPX": 2
    },
    "biases": {
      "BULLISH": 0,
      "BEARISH": 0,
      "NEUTRAL": 2
    },
    "signal_types": {
      "CHART_ANALYSIS": 2
    },
    "first_seen": "2026-04-21T16:39:29.776Z",
    "last_seen": "2026-04-21T17:07:13.282Z",
    "analyst_count": 1,
    "dominant_bias": "NEUTRAL",
    "confluence_bonus": 0
  },
  "7075": {
    "level": 7075,
    "count": 1,
    "analysts": {
      "mathemeatloaf7": 1
    },
    "tickers": {
      "SPX": 1
    },
    "biases": {
      "BULLISH": 0,
      "BEARISH": 1,
      "NEUTRAL": 0
    },
    "signal_types": {
      "CHART_ANALYSIS": 1
    },
    "first_seen": "2026-04-20T15:02:27.041Z",
    "last_seen": "2026-04-20T15:02:27.041Z",
    "analyst_count": 1,
    "dominant_bias": "BEARISH",
    "confluence_bonus": 0
  },
  "7100": {
    "level": 7100,
    "count": 1,
    "analysts": {
      "mathemeatloaf7": 1
    },
    "tickers": {
      "SPX": 1
    },
    "biases": {
      "BULLISH": 0,
      "BEARISH": 0,
      "NEUTRAL": 1
    },
    "signal_types": {
      "CHART_ANALYSIS": 1
    },
    "first_seen": "2026-04-21T19:51:25.798Z",
    "last_seen": "2026-04-21T19:51:25.798Z",
    "analyst_count": 1,
    "dominant_bias": "NEUTRAL",
    "confluence_bonus": 0
  },
  "7150": {
    "level": 7150,
    "count": 1,
    "analysts": {
      "barrysanders329": 1
    },
    "tickers": {
      "SPX": 1
    },
    "biases": {
      "BULLISH": 0,
      "BEARISH": 0,
      "NEUTRAL": 1
    },
    "signal_types": {
      "LEVEL_WATCH": 1
    },
    "first_seen": "2026-04-16T17:06:09.420Z",
    "last_seen": "2026-04-16T17:06:09.420Z",
    "analyst_count": 1,
    "dominant_bias": "NEUTRAL",
    "confluence_bonus": 0
  },
  "7300": {
    "level": 7300,
    "count": 1,
    "analysts": {
      "barrysanders329": 1
    },
    "tickers": {
      "SPX": 1
    },
    "biases": {
      "BULLISH": 0,
      "BEARISH": 0,
      "NEUTRAL": 1
    },
    "signal_types": {
      "LEVEL_WATCH": 1
    },
    "first_seen": "2026-04-16T17:06:09.420Z",
    "last_seen": "2026-04-16T17:06:09.420Z",
    "analyst_count": 1,
    "dominant_bias": "NEUTRAL",
    "confluence_bonus": 0
  },
  "7500": {
    "level": 7500,
    "count": 1,
    "analysts": {
      "kaprik0rn3": 1
    },
    "tickers": {
      "SPX": 1
    },
    "biases": {
      "BULLISH": 0,
      "BEARISH": 0,
      "NEUTRAL": 1
    },
    "signal_types": {
      "LEVEL_WATCH": 1
    },
    "first_seen": "2026-04-13T22:33:18.012Z",
    "last_seen": "2026-04-13T22:33:18.012Z",
    "analyst_count": 1,
    "dominant_bias": "NEUTRAL",
    "confluence_bonus": 0
  },
  "8000": {
    "level": 8000,
    "count": 1,
    "analysts": {
      "mathemeatloaf7": 1
    },
    "tickers": {
      "SPX": 1
    },
    "biases": {
      "BULLISH": 0,
      "BEARISH": 0,
      "NEUTRAL": 1
    },
    "signal_types": {
      "LEVEL_WATCH": 1
    },
    "first_seen": "2026-04-15T14:29:31.388Z",
    "last_seen": "2026-04-15T14:29:31.388Z",
    "analyst_count": 1,
    "dominant_bias": "NEUTRAL",
    "confluence_bonus": 0
  },
  "9000": {
    "level": 9000,
    "count": 1,
    "analysts": {
      "mathemeatloaf7": 1
    },
    "tickers": {
      "SPX": 1
    },
    "biases": {
      "BULLISH": 0,
      "BEARISH": 0,
      "NEUTRAL": 1
    },
    "signal_types": {
      "LEVEL_WATCH": 1
    },
    "first_seen": "2026-04-21T14:24:39.212Z",
    "last_seen": "2026-04-21T14:24:39.212Z",
    "analyst_count": 1,
    "dominant_bias": "NEUTRAL",
    "confluence_bonus": 0
  },
  "12345": {
    "level": 12345,
    "count": 1,
    "analysts": {
      "mathemeatloaf7": 1
    },
    "tickers": {
      "SPX": 1
    },
    "biases": {
      "BULLISH": 0,
      "BEARISH": 0,
      "NEUTRAL": 1
    },
    "signal_types": {
      "CHART_ANALYSIS": 1
    },
    "first_seen": "2026-04-21T19:51:25.798Z",
    "last_seen": "2026-04-21T19:51:25.798Z",
    "analyst_count": 1,
    "dominant_bias": "NEUTRAL",
    "confluence_bonus": 0
  }
}